README.rst
setup.cfg
setup.py
python_amazon_device_messaging.egg-info/PKG-INFO
python_amazon_device_messaging.egg-info/SOURCES.txt
python_amazon_device_messaging.egg-info/dependency_links.txt
python_amazon_device_messaging.egg-info/requires.txt
python_amazon_device_messaging.egg-info/top_level.txt
pythonadm/__init__.py